aiml_py_common_utils/__init__.py
aiml_py_common_utils/common.py
aiml_py_common_utils/log_manager.py
aiml_py_common_utils/gen_ai/__init__.py
aiml_py_common_utils/gen_ai/llm_openai.py
aiml_py_common_utils-0.0.3.dist-info/LICENSE
aiml_py_common_utils-0.0.3.dist-info/METADATA
aiml_py_common_utils-0.0.3.dist-info/WHEEL
aiml_py_common_utils-0.0.3.dist-info/top_level.txt
aiml_py_common_utils-0.0.3.dist-info/RECORD
