Metadata-Version: 2.1
Name: aiml-py-common-utils
Version: 0.0.3
Author-email: c17hawke <sunny.c17hawke@gmail.com>
License: MIT
Project-URL: Bug Tracker, https://github.com/c17hawke/aiml-py-common-utils/issues
Project-URL: Documentation, https://c17hawke.github.io/aiml-py-common-utils/
Project-URL: Source, https://github.com/c17hawke/aiml-py-common-utils
Classifier: Operating System :: OS Independent
Classifier: Programming Language :: Python :: 3.8
Classifier: Programming Language :: Python :: 3.9
Classifier: Programming Language :: Python :: 3.10
Classifier: Programming Language :: Python :: 3.11
Requires-Python: >=3.7
License-File: LICENSE
Requires-Dist: requests >=2.28.2
Requires-Dist: loguru >=0.7.2
Requires-Dist: python-box >=7.1.1
Requires-Dist: joblib >=1.3.2
Provides-Extra: testing
Requires-Dist: pytest ==7.4.4 ; extra == 'testing'
Requires-Dist: pytest-mock ==3.12.0 ; extra == 'testing'
Requires-Dist: pytest-cov ==4.1.0 ; extra == 'testing'
Requires-Dist: tox ==4.12.1 ; extra == 'testing'
Requires-Dist: ruff ==0.1.14 ; extra == 'testing'
Requires-Dist: mypy ==1.8.0 ; extra == 'testing'
